skinny_orm/__init__.py
skinny_orm/base_field.py
skinny_orm/base_orm.py
skinny_orm/exceptions.py
skinny_orm/orm.py
skinny_orm/sqlite_orm.py
skinny_orm-0.1.2.dist-info/METADATA
skinny_orm-0.1.2.dist-info/WHEEL
skinny_orm-0.1.2.dist-info/RECORD
