Metadata-Version: 2.1
Name: skinny-orm
Version: 0.1.2
Summary: 
Author: MayasMess
Author-email: amayas.messara@gmail.com
Requires-Python: >=3.9,<4.0
Classifier: Programming Language :: Python :: 3
Classifier: Programming Language :: Python :: 3.9
Classifier: Programming Language :: Python :: 3.10
Classifier: Programming Language :: Python :: 3.11
Classifier: Programming Language :: Python :: 3.12
Requires-Dist: dateparser (>=1.1.8,<2.0.0)
Requires-Dist: pytest (>=8.0.0,<9.0.0)
